transaction_counter.py
ranver_transaction_counter-0.1.dist-info/METADATA
ranver_transaction_counter-0.1.dist-info/WHEEL
ranver_transaction_counter-0.1.dist-info/entry_points.txt
ranver_transaction_counter-0.1.dist-info/top_level.txt
ranver_transaction_counter-0.1.dist-info/RECORD
