Metadata-Version: 2.1
Name: ranver-transaction-counter
Version: 0.1
Requires-Python: >=3.8
Requires-Dist: pandas
